odoo8_addon_web_widget_many2many_tags_multi_selection-8.0.0.1.0.99.dev12-py2.7-nspkg.pth
odoo8_addon_web_widget_many2many_tags_multi_selection-8.0.0.1.0.99.dev12.dist-info/METADATA
odoo8_addon_web_widget_many2many_tags_multi_selection-8.0.0.1.0.99.dev12.dist-info/RECORD
odoo8_addon_web_widget_many2many_tags_multi_selection-8.0.0.1.0.99.dev12.dist-info/WHEEL
odoo8_addon_web_widget_many2many_tags_multi_selection-8.0.0.1.0.99.dev12.dist-info/namespace_packages.txt
odoo8_addon_web_widget_many2many_tags_multi_selection-8.0.0.1.0.99.dev12.dist-info/top_level.txt
odoo_addons/web_widget_many2many_tags_multi_selection/README.rst
odoo_addons/web_widget_many2many_tags_multi_selection/__init__.py
odoo_addons/web_widget_many2many_tags_multi_selection/__openerp__.py
odoo_addons/web_widget_many2many_tags_multi_selection/i18n/ar.po
odoo_addons/web_widget_many2many_tags_multi_selection/i18n/de.po
odoo_addons/web_widget_many2many_tags_multi_selection/i18n/es.po
odoo_addons/web_widget_many2many_tags_multi_selection/i18n/eu.po
odoo_addons/web_widget_many2many_tags_multi_selection/i18n/fi.po
odoo_addons/web_widget_many2many_tags_multi_selection/i18n/fr.po
odoo_addons/web_widget_many2many_tags_multi_selection/i18n/it.po
odoo_addons/web_widget_many2many_tags_multi_selection/i18n/pt_BR.po
odoo_addons/web_widget_many2many_tags_multi_selection/i18n/sl.po
odoo_addons/web_widget_many2many_tags_multi_selection/i18n/tr.po
odoo_addons/web_widget_many2many_tags_multi_selection/i18n/web_widget_many2many_tags_multi_selection.pot
odoo_addons/web_widget_many2many_tags_multi_selection/static/description/icon.png
odoo_addons/web_widget_many2many_tags_multi_selection/static/src/js/view_form.js
odoo_addons/web_widget_many2many_tags_multi_selection/views/web_widget_many2many_tags_multi_selection.xml
