Metadata-Version: 2.1
Name: odoo8-addon-web-widget-many2many-tags-multi-selection
Version: 8.0.0.1.0.99.dev12
Summary: Tags multiple selection
Home-page: https://www.akretion.com
Author: Akretion, Odoo Community Association (OCA)
Author-email: support@odoo-community.org
License: AGPL-3
Platform: UNKNOWN
Classifier: Programming Language :: Python
Classifier: Framework :: Odoo
Classifier: License :: OSI Approved :: GNU Affero General Public License v3
Requires-Python: ~=2.7
Requires-Dist: odoo (<9.0a,>=8.0a)
